dpt/__init__.py
dptoolbox-0.0.1.dist-info/LICENSE
dptoolbox-0.0.1.dist-info/METADATA
dptoolbox-0.0.1.dist-info/WHEEL
dptoolbox-0.0.1.dist-info/top_level.txt
dptoolbox-0.0.1.dist-info/RECORD
