Metadata-Version: 2.1
Name: dptoolbox
Version: 0.0.1
Summary: DPToolbox contains various tools for managing tabular data
Home-page: https://github.com/pypa/sampleproject
Author: Kees Varekamp
Author-email: kees@mroffice.org
License: UNKNOWN
Platform: UNKNOWN
Classifier: Programming Language :: Python :: 3
Classifier: License :: OSI Approved :: MIT License
Classifier: Operating System :: OS Independent
